xortool/__init__.py
xortool/args.py
xortool/charset.py
xortool/colors.py
xortool/libcolors.py
xortool/routine.py
xortool/tool_main.py
xortool/tool_xor.py
xortool-1.1.0.dist-info/METADATA
xortool-1.1.0.dist-info/WHEEL
xortool-1.1.0.dist-info/entry_points.txt
xortool-1.1.0.dist-info/RECORD
