Metadata-Version: 2.3
Name: xortool
Version: 1.1.0
Summary: A tool to analyze multi-byte xor cipher
License: MIT
Keywords: xor,xortool,cryptanalysis
Author: hellman
Requires-Python: >=3.6,<4.0
Classifier: Intended Audience :: Information Technology
Classifier: Intended Audience :: Science/Research
Classifier: License :: OSI Approved :: MIT License
Classifier: Programming Language :: Python :: 3
Classifier: Programming Language :: Python :: 3.6
Classifier: Programming Language :: Python :: 3.7
Classifier: Programming Language :: Python :: 3.8
Classifier: Programming Language :: Python :: 3.9
Classifier: Programming Language :: Python :: 3.10
Classifier: Programming Language :: Python :: 3.11
Classifier: Programming Language :: Python :: 3.12
Classifier: Programming Language :: Python :: 3.13
Classifier: Topic :: Security :: Cryptography
Requires-Dist: docopt (>=0.6.2,<0.7.0)
Project-URL: homepage, http://github.com/hellman/xortool
